pyseim/__init__.py
pyseim/icon/icon.icns
pyseim/icon/icon.png
pyseim/main.py
pyseim/rawspice.raw
pyseim/refresh.png
pyseim/report.txt
pyseim/show.png
pyseim/test.cir
pyseim/tmp.cir
pyseim-0.1.1.dist-info/entry_points.txt
pyseim-0.1.1.dist-info/LICENSE
pyseim-0.1.1.dist-info/WHEEL
pyseim-0.1.1.dist-info/METADATA
pyseim-0.1.1.dist-info/RECORD
